{
  "id": "ice-storm",
  "kind": "spell",
  "name": "Ice Storm",
  "edition": "2024",
  "level": 4,
  "school": "Evocation",
  "classes": [
    "druid",
    "sorcerer",
    "wizard"
  ],
  "ritual": false,
  "concentration": false,
  "castingTime": "Action",
  "range": "300 feet",
  "components": [
    "V",
    "S",
    "M"
  ],
  "material": "a mitten",
  "duration": "Instantaneous",
  "text": "# Ice Storm\n*4th-Level Evocation (Druid, Sorcerer, Wizard)*\n**Casting Time:** Action\n**Range:** 300 feet\n**Components:** V, S, M (a mitten)\n**Duration:** Instantaneous\n\nHail falls in a 20-foot-radius, 40-foot-high Cylinder centered on a point within range. Each creature in the Cylinder makes a Dexterity saving throw. A creature takes 2d10 Bludgeoning damage and 4d6 Cold damage on a failed save or half as much damage on a successful one.\n\nHailstones turn ground in the Cylinder into Difficult Terrain until the end of your next turn.\n\n**Using a Higher-Level Spell Slot.** The Bludgeoning damage increases by 1d10 for each spell slot level above 4."
}
