{
  "id": "farmer",
  "kind": "background",
  "name": "Farmer",
  "edition": "2024",
  "abilityScores": [
    "STR",
    "CON",
    "WIS"
  ],
  "originFeat": "tough",
  "skillProficiencies": [
    "animal-handling",
    "nature"
  ],
  "toolProficiency": "Carpenter's Tools",
  "text": "You grew up close to the land. Years tending animals and cultivating the earth rewarded you with patience and good health. You have a keen appreciation for nature’s bounty alongside a healthy respect for nature's wrath.\n\n**Ability Scores:** Strength, Constitution, Wisdom\n\n**Feat:** Tough\n\n**Skill Proficiencies:** Animal Handling and Nature\n\n**Tool Proficiency:** Carpenter's Tools\n\n**Equipment:** Choose A or B: (A) Sickle, Carpenter's Tools, Healer's Kit, Iron Pot, Shovel, Traveler's Clothes, 30 GP; or (B) 50 GP"
}
